{
  "annotations": {
    "list": [
      {
        "builtIn": 1,
        "datasource": {
          "type": "grafana",
          "uid": "-- Grafana --"
        },
        "enable": true,
        "hide": true,
        "iconColor": "rgba(0, 211, 255, 1)",
        "name": "Annotations & Alerts",
        "type": "dashboard"
      }
    ]
  },
  "editable": true,
  "fiscalYearStartMonth": 0,
  "graphTooltip": 0,
  "id": 6,
  "links": [],
  "panels": [
    {
      "datasource": {
        "type": "grafana-bigquery-datasource",
        "uid": "P0871A590F805E5CD"
      },
      "fieldConfig": {
        "defaults": {
          "color": {
            "mode": "thresholds"
          },
          "links": [
            {
              "title": "Ejecuciones",
              "url": "/d/72f28c4b-577c-49b4-8b32-772725591897/ejecuciones-y-predicciones?orgId=1"
            }
          ],
          "mappings": [],
          "thresholds": {
            "mode": "absolute",
            "steps": [
              {
                "color": "yellow"
              },
              {
                "color": "red",
                "value": 80
              }
            ]
          }
        },
        "overrides": []
      },
      "gridPos": {
        "h": 6,
        "w": 3,
        "x": 0,
        "y": 0
      },
      "id": 2,
      "options": {
        "colorMode": "value",
        "graphMode": "area",
        "justifyMode": "auto",
        "orientation": "auto",
        "percentChangeColorMode": "standard",
        "reduceOptions": {
          "calcs": [
            "lastNotNull"
          ],
          "fields": "",
          "values": false
        },
        "showPercentChange": false,
        "textMode": "auto",
        "wideLayout": true
      },
      "pluginVersion": "12.0.2",
      "targets": [
        {
          "dataset": "NTTData",
          "datasource": {
            "type": "grafana-bigquery-datasource",
            "uid": "P0871A590F805E5CD"
          },
          "editorMode": "code",
          "format": 1,
          "location": "",
          "project": "tfm-nttdata",
          "rawQuery": true,
          "rawSql": "SELECT COUNT(DISTINCT Oficina)  AS oficinas_activas\r\nFROM `tfm-nttdata.NTTData.metricas`\r\nWHERE Oficina IN UNNEST([${Oficina}])",
          "refId": "A",
          "sql": {
            "columns": [
              {
                "name": "MAX",
                "parameters": [
                  {
                    "name": "Oficina",
                    "type": "functionParameter"
                  }
                ],
                "type": "function"
              }
            ],
            "groupBy": [
              {
                "property": {
                  "type": "string"
                },
                "type": "groupBy"
              }
            ],
            "limit": 50
          },
          "table": "metricas"
        }
      ],
      "title": "Número de oficinas",
      "type": "stat"
    },
    {
      "datasource": {
        "type": "grafana-bigquery-datasource",
        "uid": "P0871A590F805E5CD"
      },
      "fieldConfig": {
        "defaults": {
          "color": {
            "mode": "thresholds"
          },
          "mappings": [],
          "thresholds": {
            "mode": "absolute",
            "steps": [
              {
                "color": "yellow"
              },
              {
                "color": "red",
                "value": 80
              }
            ]
          }
        },
        "overrides": []
      },
      "gridPos": {
        "h": 6,
        "w": 3,
        "x": 3,
        "y": 0
      },
      "id": 3,
      "options": {
        "colorMode": "value",
        "graphMode": "area",
        "justifyMode": "auto",
        "orientation": "auto",
        "percentChangeColorMode": "standard",
        "reduceOptions": {
          "calcs": [
            "lastNotNull"
          ],
          "fields": "",
          "values": false
        },
        "showPercentChange": false,
        "textMode": "auto",
        "wideLayout": true
      },
      "pluginVersion": "12.0.2",
      "targets": [
        {
          "datasource": {
            "type": "grafana-bigquery-datasource",
            "uid": "P0871A590F805E5CD"
          },
          "editorMode": "code",
          "format": 1,
          "location": "",
          "project": "tfm-nttdata",
          "rawQuery": true,
          "rawSql": "SELECT COUNT(DISTINCT Model_id) AS modelos_activos\r\nFROM `tfm-nttdata.NTTData.metricas`\r\n",
          "refId": "A",
          "sql": {
            "columns": [
              {
                "parameters": [],
                "type": "function"
              }
            ],
            "groupBy": [
              {
                "property": {
                  "type": "string"
                },
                "type": "groupBy"
              }
            ],
            "limit": 50
          }
        }
      ],
      "title": "Número de modelos",
      "type": "stat"
    },
    {
      "datasource": {
        "type": "grafana-bigquery-datasource",
        "uid": "P0871A590F805E5CD"
      },
      "fieldConfig": {
        "defaults": {
          "color": {
            "fixedColor": "semi-dark-blue",
            "mode": "continuous-BlPu"
          },
          "custom": {
            "axisBorderShow": false,
            "axisCenteredZero": false,
            "axisColorMode": "text",
            "axisGridShow": false,
            "axisLabel": "",
            "axisPlacement": "auto",
            "barAlignment": 0,
            "barWidthFactor": 0.6,
            "drawStyle": "line",
            "fillOpacity": 100,
            "gradientMode": "hue",
            "hideFrom": {
              "legend": false,
              "tooltip": false,
              "viz": false
            },
            "insertNulls": false,
            "lineInterpolation": "linear",
            "lineWidth": 2,
            "pointSize": 1,
            "scaleDistribution": {
              "type": "linear"
            },
            "showPoints": "auto",
            "spanNulls": false,
            "stacking": {
              "group": "A",
              "mode": "none"
            },
            "thresholdsStyle": {
              "mode": "off"
            }
          },
          "mappings": [],
          "thresholds": {
            "mode": "absolute",
            "steps": [
              {
                "color": "blue"
              },
              {
                "color": "red",
                "value": 80
              }
            ]
          }
        },
        "overrides": []
      },
      "gridPos": {
        "h": 8,
        "w": 13,
        "x": 6,
        "y": 0
      },
      "id": 5,
      "options": {
        "legend": {
          "calcs": [],
          "displayMode": "table",
          "placement": "right",
          "showLegend": true
        },
        "tooltip": {
          "hideZeros": false,
          "mode": "single",
          "sort": "none"
        }
      },
      "pluginVersion": "12.0.2",
      "targets": [
        {
          "datasource": {
            "type": "grafana-bigquery-datasource",
            "uid": "P0871A590F805E5CD"
          },
          "editorMode": "code",
          "format": 1,
          "location": "",
          "project": "tfm-nttdata",
          "rawQuery": true,
          "rawSql": "SELECT\r\n  TIMESTAMP(DATE_TRUNC(Execution_day, MONTH)) AS time,\r\n  SUM(Total_inference_energy_wh) / 1000 AS Energia_total_kWh\r\nFROM `tfm-nttdata.NTTData.metricas`\r\nWHERE Execution_day IS NOT NULL\r\n  AND Oficina IN UNNEST([${Oficina}])\r\nGROUP BY\r\n  time\r\nORDER BY\r\n  time\r\n",
          "refId": "A",
          "sql": {
            "columns": [
              {
                "parameters": [],
                "type": "function"
              }
            ],
            "groupBy": [
              {
                "property": {
                  "type": "string"
                },
                "type": "groupBy"
              }
            ],
            "limit": 50
          }
        }
      ],
      "title": "Desglose de la energia gastada por mes",
      "type": "timeseries"
    },
    {
      "datasource": {
        "type": "grafana-bigquery-datasource",
        "uid": "P0871A590F805E5CD"
      },
      "fieldConfig": {
        "defaults": {
          "color": {
            "mode": "thresholds"
          },
          "links": [
            {
              "title": "EPT-Interior",
              "url": "/d/ber0h8xem5gcgb/ept-interior?orgId=1"
            }
          ],
          "mappings": [],
          "thresholds": {
            "mode": "absolute",
            "steps": [
              {
                "color": "blue"
              },
              {
                "color": "light-blue",
                "value": 80
              }
            ]
          },
          "unit": "kWh"
        },
        "overrides": []
      },
      "gridPos": {
        "h": 8,
        "w": 5,
        "x": 19,
        "y": 0
      },
      "id": 4,
      "options": {
        "colorMode": "background",
        "graphMode": "area",
        "justifyMode": "auto",
        "orientation": "auto",
        "percentChangeColorMode": "standard",
        "reduceOptions": {
          "calcs": [
            "lastNotNull"
          ],
          "fields": "",
          "values": false
        },
        "showPercentChange": false,
        "textMode": "value",
        "wideLayout": true
      },
      "pluginVersion": "12.0.2",
      "targets": [
        {
          "datasource": {
            "type": "grafana-bigquery-datasource",
            "uid": "P0871A590F805E5CD"
          },
          "editorMode": "code",
          "format": 1,
          "location": "",
          "project": "tfm-nttdata",
          "rawQuery": true,
          "rawSql": "SELECT SUM(EPT_kwh)\r\nFROM `tfm-nttdata.NTTData.metricas` \r\nWHERE Execution_day IS NOT NULL\r\n  AND Oficina IN UNNEST([${Oficina}])",
          "refId": "A",
          "sql": {
            "columns": [
              {
                "parameters": [],
                "type": "function"
              }
            ],
            "groupBy": [
              {
                "property": {
                  "type": "string"
                },
                "type": "groupBy"
              }
            ],
            "limit": 50
          }
        }
      ],
      "title": "Energia utilizada",
      "type": "stat"
    },
    {
      "datasource": {
        "type": "grafana-bigquery-datasource",
        "uid": "P0871A590F805E5CD"
      },
      "fieldConfig": {
        "defaults": {
          "color": {
            "mode": "thresholds"
          },
          "custom": {
            "hideFrom": {
              "legend": false,
              "tooltip": false,
              "viz": false
            }
          },
          "links": [],
          "mappings": [],
          "thresholds": {
            "mode": "absolute",
            "steps": [
              {
                "color": "yellow"
              },
              {
                "color": "red",
                "value": 80
              }
            ]
          }
        },
        "overrides": [
          {
            "matcher": {
              "id": "byName",
              "options": "Oficina"
            },
            "properties": [
              {
                "id": "links",
                "value": [
                  {
                    "title": "Filtrar por esta oficina",
                    "url": "/d/${__dashboard.uid}/${__dashboard.slug}?var-Oficina=${__data.fields.Oficina}\r\n"
                  }
                ]
              }
            ]
          }
        ]
      },
      "gridPos": {
        "h": 18,
        "w": 6,
        "x": 0,
        "y": 6
      },
      "id": 1,
      "options": {
        "basemap": {
          "config": {},
          "name": "Layer 0",
          "type": "default"
        },
        "controls": {
          "mouseWheelZoom": true,
          "showAttribution": false,
          "showDebug": false,
          "showMeasure": false,
          "showScale": false,
          "showZoom": true
        },
        "layers": [
          {
            "config": {
              "showLegend": false,
              "style": {
                "color": {
                  "field": "oficina_id",
                  "fixed": "dark-green"
                },
                "opacity": 1,
                "rotation": {
                  "fixed": 0,
                  "max": 360,
                  "min": -360,
                  "mode": "mod"
                },
                "size": {
                  "fixed": 10,
                  "max": 15,
                  "min": 2
                },
                "symbol": {
                  "fixed": "img/icons/marker/circle.svg",
                  "mode": "fixed"
                },
                "symbolAlign": {
                  "horizontal": "center",
                  "vertical": "center"
                },
                "text": {
                  "field": "Oficina",
                  "fixed": "",
                  "mode": "fixed"
                },
                "textConfig": {
                  "offsetX": 0,
                  "offsetY": 0,
                  "textAlign": "center",
                  "textBaseline": "middle"
                }
              }
            },
            "location": {
              "mode": "auto"
            },
            "name": "Layer 1",
            "tooltip": true,
            "type": "markers"
          }
        ],
        "tooltip": {
          "mode": "details"
        },
        "view": {
          "allLayers": true,
          "id": "coords",
          "lat": 39.379387,
          "lon": -1.696818,
          "zoom": 5.98
        }
      },
      "pluginVersion": "12.0.2",
      "targets": [
        {
          "dataset": "NTTData",
          "datasource": {
            "type": "grafana-bigquery-datasource",
            "uid": "P0871A590F805E5CD"
          },
          "editorMode": "code",
          "format": 1,
          "location": "",
          "project": "tfm-nttdata",
          "rawQuery": true,
          "rawSql": "SELECT\r\n  Oficina,\r\n  DENSE_RANK() OVER (ORDER BY Oficina) AS oficina_id,\r\n  AVG(Latitud) AS latitude,\r\n  AVG(Longitud) AS longitude\r\nFROM\r\n  `tfm-nttdata.NTTData.metricas`\r\nWHERE\r\n  Latitud IS NOT NULL\r\n  AND Longitud IS NOT NULL\r\nGROUP BY\r\n  Oficina\r\n",
          "refId": "A",
          "sql": {
            "columns": [
              {
                "parameters": [
                  {
                    "name": "Longitud",
                    "type": "functionParameter"
                  }
                ],
                "type": "function"
              }
            ],
            "groupBy": [
              {
                "property": {
                  "type": "string"
                },
                "type": "groupBy"
              }
            ],
            "limit": 50
          },
          "table": "metricas"
        }
      ],
      "title": "Distribución de oficinas",
      "type": "geomap"
    },
    {
      "datasource": {
        "type": "grafana-bigquery-datasource",
        "uid": "P0871A590F805E5CD"
      },
      "fieldConfig": {
        "defaults": {
          "color": {
            "mode": "thresholds"
          },
          "links": [
            {
              "title": "CPT interior",
              "url": "/d/d5e39d73-6da7-47f0-b28d-48fa8f9c3cdc/cpt-interior?orgId=1"
            }
          ],
          "mappings": [],
          "thresholds": {
            "mode": "absolute",
            "steps": [
              {
                "color": "blue"
              },
              {
                "color": "light-red",
                "value": 80
              }
            ]
          },
          "unit": "CO2"
        },
        "overrides": []
      },
      "gridPos": {
        "h": 8,
        "w": 5,
        "x": 6,
        "y": 8
      },
      "id": 7,
      "options": {
        "colorMode": "background",
        "graphMode": "area",
        "justifyMode": "auto",
        "orientation": "auto",
        "percentChangeColorMode": "standard",
        "reduceOptions": {
          "calcs": [
            "lastNotNull"
          ],
          "fields": "",
          "values": false
        },
        "showPercentChange": false,
        "textMode": "value",
        "wideLayout": true
      },
      "pluginVersion": "12.0.2",
      "targets": [
        {
          "datasource": {
            "type": "grafana-bigquery-datasource",
            "uid": "P0871A590F805E5CD"
          },
          "editorMode": "code",
          "format": 1,
          "location": "",
          "project": "tfm-nttdata",
          "rawQuery": true,
          "rawSql": "SELECT SUM(CPT_kg_co2)\r\nFROM `tfm-nttdata.NTTData.metricas` \r\nWHERE Oficina IN UNNEST([${Oficina}])",
          "refId": "A",
          "sql": {
            "columns": [
              {
                "parameters": [],
                "type": "function"
              }
            ],
            "groupBy": [
              {
                "property": {
                  "type": "string"
                },
                "type": "groupBy"
              }
            ],
            "limit": 50
          }
        }
      ],
      "title": "Emisiones de CO2 totales",
      "type": "stat"
    },
    {
      "datasource": {
        "type": "grafana-bigquery-datasource",
        "uid": "P0871A590F805E5CD"
      },
      "fieldConfig": {
        "defaults": {
          "color": {
            "mode": "continuous-GrYlRd"
          },
          "custom": {
            "axisBorderShow": false,
            "axisCenteredZero": false,
            "axisColorMode": "text",
            "axisGridShow": false,
            "axisLabel": "",
            "axisPlacement": "auto",
            "barAlignment": 0,
            "barWidthFactor": 0.6,
            "drawStyle": "line",
            "fillOpacity": 92,
            "gradientMode": "scheme",
            "hideFrom": {
              "legend": false,
              "tooltip": false,
              "viz": false
            },
            "insertNulls": false,
            "lineInterpolation": "smooth",
            "lineWidth": 3,
            "pointSize": 5,
            "scaleDistribution": {
              "type": "linear"
            },
            "showPoints": "never",
            "spanNulls": false,
            "stacking": {
              "group": "A",
              "mode": "none"
            },
            "thresholdsStyle": {
              "mode": "off"
            }
          },
          "mappings": [],
          "thresholds": {
            "mode": "absolute",
            "steps": [
              {
                "color": "green"
              },
              {
                "color": "red",
                "value": 80
              }
            ]
          }
        },
        "overrides": []
      },
      "gridPos": {
        "h": 8,
        "w": 13,
        "x": 11,
        "y": 8
      },
      "id": 6,
      "options": {
        "legend": {
          "calcs": [],
          "displayMode": "table",
          "placement": "right",
          "showLegend": true
        },
        "tooltip": {
          "hideZeros": false,
          "mode": "single",
          "sort": "none"
        }
      },
      "pluginVersion": "12.0.2",
      "targets": [
        {
          "datasource": {
            "type": "grafana-bigquery-datasource",
            "uid": "P0871A590F805E5CD"
          },
          "editorMode": "code",
          "format": 1,
          "location": "",
          "project": "tfm-nttdata",
          "rawQuery": true,
          "rawSql": "SELECT\r\n  TIMESTAMP(DATE_TRUNC(Execution_day, MONTH)) AS time,\r\n  SUM(CPT_kg_co2) AS Total_CO2\r\nFROM\r\n  `tfm-nttdata.NTTData.metricas`\r\nWHERE Execution_day IS NOT NULL\r\n  AND Oficina IN UNNEST([${Oficina}])\r\nGROUP BY\r\n  time\r\nORDER BY\r\n  time\r\n",
          "refId": "A",
          "sql": {
            "columns": [
              {
                "parameters": [],
                "type": "function"
              }
            ],
            "groupBy": [
              {
                "property": {
                  "type": "string"
                },
                "type": "groupBy"
              }
            ],
            "limit": 50
          }
        }
      ],
      "title": "Consumo de CO2 por mes",
      "type": "timeseries"
    },
    {
      "datasource": {
        "type": "grafana-bigquery-datasource",
        "uid": "P0871A590F805E5CD"
      },
      "description": "",
      "fieldConfig": {
        "defaults": {
          "color": {
            "mode": "thresholds"
          },
          "links": [
            {
              "targetBlank": false,
              "title": "Carbon_efficiency_interior",
              "url": "/d/b2451c87-03a6-4ed7-92d2-5246e43381b2/carbon-efficiency?orgId=1"
            }
          ],
          "mappings": [],
          "thresholds": {
            "mode": "absolute",
            "steps": [
              {
                "color": "orange"
              },
              {
                "color": "red",
                "value": 80
              }
            ]
          },
          "unit": "percent"
        },
        "overrides": []
      },
      "gridPos": {
        "h": 8,
        "w": 4,
        "x": 6,
        "y": 16
      },
      "id": 12,
      "options": {
        "colorMode": "value",
        "graphMode": "area",
        "justifyMode": "auto",
        "orientation": "auto",
        "percentChangeColorMode": "standard",
        "reduceOptions": {
          "calcs": [
            "lastNotNull"
          ],
          "fields": "",
          "values": false
        },
        "showPercentChange": false,
        "text": {
          "titleSize": 1
        },
        "textMode": "value_and_name",
        "wideLayout": false
      },
      "pluginVersion": "12.0.2",
      "targets": [
        {
          "dataset": "NTTData",
          "datasource": {
            "type": "grafana-bigquery-datasource",
            "uid": "P0871A590F805E5CD"
          },
          "editorMode": "code",
          "format": 1,
          "location": "",
          "project": "tfm-nttdata",
          "rawQuery": true,
          "rawSql": "SELECT\r\n  TIMESTAMP(DATE_TRUNC(Execution_day, MONTH)) AS time,\r\n  ROUND(AVG(Carbon_efficiency), 2) AS porcentaje_no_usado\r\nFROM `tfm-nttdata.NTTData.metricas`\r\nWHERE Execution_day IS NOT NULL\r\n  AND Carbon_efficiency IS NOT NULL\r\n  AND Oficina IN UNNEST([${Oficina}])\r\nGROUP BY time\r\nORDER BY time\r\n",
          "refId": "A",
          "sql": {
            "columns": [
              {
                "parameters": [],
                "type": "function"
              }
            ],
            "groupBy": [
              {
                "property": {
                  "type": "string"
                },
                "type": "groupBy"
              }
            ],
            "limit": 50
          },
          "table": "metricas"
        }
      ],
      "title": "Precisión por KG de CO2 emitido",
      "transparent": true,
      "type": "stat"
    },
    {
      "datasource": {
        "type": "grafana-bigquery-datasource",
        "uid": "P0871A590F805E5CD"
      },
      "description": "",
      "fieldConfig": {
        "defaults": {
          "color": {
            "mode": "thresholds"
          },
          "links": [
            {
              "targetBlank": false,
              "title": "DWR Inteiror",
              "url": "/d/aer0ilxdhsohsf/dws-interior?orgId=1"
            }
          ],
          "mappings": [],
          "thresholds": {
            "mode": "absolute",
            "steps": [
              {
                "color": "semi-dark-purple"
              },
              {
                "color": "red",
                "value": 80
              }
            ]
          },
          "unit": "percent"
        },
        "overrides": [
          {
            "matcher": {
              "id": "byName",
              "options": "porcentaje_no_usado"
            },
            "properties": [
              {
                "id": "displayName",
                "value": "Porcentaje de datos no usado"
              }
            ]
          }
        ]
      },
      "gridPos": {
        "h": 8,
        "w": 4,
        "x": 10,
        "y": 16
      },
      "id": 9,
      "options": {
        "colorMode": "value",
        "graphMode": "area",
        "justifyMode": "auto",
        "orientation": "auto",
        "percentChangeColorMode": "standard",
        "reduceOptions": {
          "calcs": [
            "lastNotNull"
          ],
          "fields": "",
          "values": false
        },
        "showPercentChange": false,
        "text": {
          "titleSize": 1
        },
        "textMode": "value_and_name",
        "wideLayout": false
      },
      "pluginVersion": "12.0.2",
      "targets": [
        {
          "dataset": "NTTData",
          "datasource": {
            "type": "grafana-bigquery-datasource",
            "uid": "P0871A590F805E5CD"
          },
          "editorMode": "code",
          "format": 1,
          "location": "",
          "project": "tfm-nttdata",
          "rawQuery": true,
          "rawSql": "SELECT\r\n  TIMESTAMP(DATE_TRUNC(Execution_day, MONTH)) AS time,\r\n  ROUND(AVG(Data_Waste_Ratio) * 100, 2) AS porcentaje_no_usado\r\nFROM `tfm-nttdata.NTTData.metricas`\r\nWHERE Execution_day IS NOT NULL\r\n  AND Data_Waste_Ratio IS NOT NULL\r\n  AND Oficina IN UNNEST([${Oficina}])\r\nGROUP BY time\r\nORDER BY time\r\n",
          "refId": "A",
          "sql": {
            "columns": [
              {
                "parameters": [],
                "type": "function"
              }
            ],
            "groupBy": [
              {
                "property": {
                  "type": "string"
                },
                "type": "groupBy"
              }
            ],
            "limit": 50
          },
          "table": "metricas"
        }
      ],
      "title": "Porcentaje de datos no usados ",
      "transparent": true,
      "type": "stat"
    },
    {
      "datasource": {
        "type": "grafana-bigquery-datasource",
        "uid": "P0871A590F805E5CD"
      },
      "fieldConfig": {
        "defaults": {
          "color": {
            "mode": "thresholds"
          },
          "links": [
            {
              "title": "Mfs-Interior",
              "url": "/d/d30375d3-cfb5-4cae-ad21-338b09a7a129/mfs-interior?orgId=1"
            }
          ],
          "mappings": [],
          "thresholds": {
            "mode": "absolute",
            "steps": [
              {
                "color": "green"
              },
              {
                "color": "red",
                "value": 80
              }
            ]
          },
          "unit": "percent"
        },
        "overrides": [
          {
            "matcher": {
              "id": "byName",
              "options": "porcentaje_no_usado"
            },
            "properties": []
          }
        ]
      },
      "gridPos": {
        "h": 8,
        "w": 5,
        "x": 14,
        "y": 16
      },
      "id": 10,
      "options": {
        "colorMode": "none",
        "graphMode": "area",
        "justifyMode": "auto",
        "orientation": "horizontal",
        "percentChangeColorMode": "standard",
        "reduceOptions": {
          "calcs": [
            "lastNotNull"
          ],
          "fields": "",
          "values": false
        },
        "showPercentChange": false,
        "text": {
          "titleSize": 1
        },
        "textMode": "value_and_name",
        "wideLayout": false
      },
      "pluginVersion": "12.0.2",
      "targets": [
        {
          "dataset": "NTTData",
          "editorMode": "code",
          "format": 1,
          "location": "",
          "project": "tfm-nttdata",
          "rawQuery": true,
          "rawSql": "SELECT\r\n  TIMESTAMP(DATE_TRUNC(Execution_day, MONTH)) AS time,\r\n  ROUND(AVG(Model_Footprint_Score), 2) AS model_footprint_score\r\nFROM `tfm-nttdata.NTTData.metricas`\r\nWHERE Execution_day IS NOT NULL\r\n  AND Model_Footprint_Score IS NOT NULL\r\n  AND Model_accuracy < 1\r\n  AND Oficina IN UNNEST([${Oficina}])\r\nGROUP BY time\r\nORDER BY time\r\n",
          "refId": "A",
          "sql": {
            "columns": [
              {
                "parameters": [],
                "type": "function"
              }
            ],
            "groupBy": [
              {
                "property": {
                  "type": "string"
                },
                "type": "groupBy"
              }
            ],
            "limit": 50
          },
          "table": "metricas"
        }
      ],
      "title": "Media de MFS ",
      "transparent": true,
      "type": "stat"
    },
    {
      "datasource": {
        "type": "grafana-bigquery-datasource",
        "uid": "P0871A590F805E5CD"
      },
      "fieldConfig": {
        "defaults": {
          "color": {
            "mode": "thresholds"
          },
          "links": [
            {
              "targetBlank": false,
              "title": "Carbon efficiency Inteiror",
              "url": "/d/be3186d5-34f7-44a1-9cdd-b65de59473d6/epp-y-total-predicciones?orgId=1"
            }
          ],
          "mappings": [],
          "thresholds": {
            "mode": "absolute",
            "steps": [
              {
                "color": "light-yellow"
              },
              {
                "color": "red",
                "value": 80
              }
            ]
          },
          "unit": "Wh"
        },
        "overrides": [
          {
            "matcher": {
              "id": "byName",
              "options": "porcentaje_no_usado"
            },
            "properties": [
              {
                "id": "displayName",
                "value": "Porcentaje de datos no usado"
              }
            ]
          }
        ]
      },
      "gridPos": {
        "h": 8,
        "w": 5,
        "x": 19,
        "y": 16
      },
      "id": 11,
      "options": {
        "colorMode": "value",
        "graphMode": "area",
        "justifyMode": "auto",
        "orientation": "auto",
        "percentChangeColorMode": "standard",
        "reduceOptions": {
          "calcs": [
            "lastNotNull"
          ],
          "fields": "",
          "values": false
        },
        "showPercentChange": false,
        "text": {
          "titleSize": 1
        },
        "textMode": "value_and_name",
        "wideLayout": false
      },
      "pluginVersion": "12.0.2",
      "targets": [
        {
          "dataset": "NTTData",
          "editorMode": "code",
          "format": 1,
          "location": "",
          "project": "tfm-nttdata",
          "rawQuery": true,
          "rawSql": "SELECT\r\n  TIMESTAMP(DATE_TRUNC(Execution_day, MONTH)) AS time,\r\n  ROUND(AVG(Epp_Wh), 2) AS porcentaje_no_usado\r\nFROM `tfm-nttdata.NTTData.metricas`\r\nWHERE Execution_day IS NOT NULL\r\n  AND Epp_Wh IS NOT NULL\r\n  AND Oficina IN UNNEST([${Oficina}])\r\nGROUP BY time\r\nORDER BY time\r\n",
          "refId": "A",
          "sql": {
            "columns": [
              {
                "parameters": [],
                "type": "function"
              }
            ],
            "groupBy": [
              {
                "property": {
                  "type": "string"
                },
                "type": "groupBy"
              }
            ],
            "limit": 50
          },
          "table": "metricas"
        }
      ],
      "title": "Energia usada para una prediccioón",
      "transparent": true,
      "type": "stat"
    }
  ],
  "preload": false,
  "refresh": "",
  "schemaVersion": 41,
  "tags": [],
  "templating": {
    "list": [
      {
        "allowCustomValue": true,
        "current": {
          "text": "All",
          "value": "All"
        },
        "datasource": {
          "type": "grafana-bigquery-datasource",
          "uid": "P0871A590F805E5CD"
        },
        "definition": "",
        "includeAll": true,
        "multi": true,
        "name": "Oficina",
        "options": [],
        "query": {
          "editorMode": "code",
          "format": 1,
          "location": "",
          "project": "tfm-nttdata",
          "rawQuery": true,
          "rawSql": "SELECT DISTINCT Oficina FROM `tfm-nttdata.NTTData.metricas` ORDER BY Oficina\r\n",
          "refId": "tempvar",
          "sql": {
            "columns": [
              {
                "parameters": [],
                "type": "function"
              }
            ],
            "groupBy": [
              {
                "property": {
                  "type": "string"
                },
                "type": "groupBy"
              }
            ],
            "limit": 50
          }
        },
        "refresh": 1,
        "regex": "",
        "type": "query"
      }
    ]
  },
  "time": {
    "from": "2023-12-31T01:38:06.379Z",
    "to": "2025-03-03T12:05:23.290Z"
  },
  "timepicker": {},
  "timezone": "browser",
  "title": "Principal Nuevo",
  "uid": "berb2yrcux0qoe",
  "version": 1
}